I18nLibrary/__init__.py
I18nLibrary/base/__init__.py
I18nLibrary/base/robotlibcore.py
robotframework_I18nLibrary-0.1.4.dist-info/LICENSE
robotframework_I18nLibrary-0.1.4.dist-info/METADATA
robotframework_I18nLibrary-0.1.4.dist-info/WHEEL
robotframework_I18nLibrary-0.1.4.dist-info/top_level.txt
robotframework_I18nLibrary-0.1.4.dist-info/RECORD
