Metadata-Version: 2.1
Name: robotframework-I18nLibrary
Version: 0.1.4
Summary: I18nLibrary translator library for support in robotframework.
Home-page: https://github.com/qahive/robotframework-I18nLibrary
Author: QA Hive Co.,Ltd
Author-email: support@qahive.com
License: Apache License 2.0
Keywords: robotframework testing automation data-driven qahive
Platform: any
Classifier: Programming Language :: Python :: 3
Classifier: Programming Language :: Python :: 3.6
Classifier: Programming Language :: Python :: 3.7
Classifier: License :: OSI Approved :: Apache Software License
Classifier: Operating System :: OS Independent
Classifier: Topic :: Software Development :: Testing
Classifier: Topic :: Software Development :: Testing :: Acceptance
Classifier: Framework :: Robot Framework
Requires-Python: >3.5
Requires-Dist: python-i18n
Requires-Dist: PyYAML
